MANIFEST.in
README.md
setup.py
counterparty_lib.egg-info/PKG-INFO
counterparty_lib.egg-info/SOURCES.txt
counterparty_lib.egg-info/dependency_links.txt
counterparty_lib.egg-info/not-zip-safe
counterparty_lib.egg-info/requires.txt
counterparty_lib.egg-info/top_level.txt
counterpartylib/__init__.py
counterpartylib/mainnet_burns.csv
counterpartylib/protocol_changes.json
counterpartylib/server.py
counterpartylib/lib/__init__.py
counterpartylib/lib/address.py
counterpartylib/lib/api.py
counterpartylib/lib/blocks.py
counterpartylib/lib/check.py
counterpartylib/lib/config.py
counterpartylib/lib/database.py
counterpartylib/lib/exceptions.py
counterpartylib/lib/log.py
counterpartylib/lib/message_type.py
counterpartylib/lib/script.py
counterpartylib/lib/transaction.py
counterpartylib/lib/util.py
counterpartylib/lib/util_windows.py
counterpartylib/lib/backend/__init__.py
counterpartylib/lib/backend/addrindex.py
counterpartylib/lib/backend/btcd.py
counterpartylib/lib/kickstart/__init__.py
counterpartylib/lib/kickstart/bc_data_stream.py
counterpartylib/lib/kickstart/blocks_parser.py
counterpartylib/lib/kickstart/exceptions.py
counterpartylib/lib/kickstart/utils.py
counterpartylib/lib/messages/__init__.py
counterpartylib/lib/messages/bet.py
counterpartylib/lib/messages/broadcast.py
counterpartylib/lib/messages/btcpay.py
counterpartylib/lib/messages/burn.py
counterpartylib/lib/messages/cancel.py
counterpartylib/lib/messages/destroy.py
counterpartylib/lib/messages/dividend.py
counterpartylib/lib/messages/execute.py
counterpartylib/lib/messages/issuance.py
counterpartylib/lib/messages/order.py
counterpartylib/lib/messages/publish.py
counterpartylib/lib/messages/rps.py
counterpartylib/lib/messages/rpsresolve.py
counterpartylib/lib/messages/send.py
counterpartylib/lib/messages/scriptlib/__init__.py
counterpartylib/lib/messages/scriptlib/blocks.py
counterpartylib/lib/messages/scriptlib/opcodes.py
counterpartylib/lib/messages/scriptlib/processblock.py
counterpartylib/lib/messages/scriptlib/rlp.py
counterpartylib/lib/messages/scriptlib/utils.py
counterpartylib/lib/messages/versions/__init__.py
counterpartylib/lib/messages/versions/enhanced_send.py
counterpartylib/lib/messages/versions/send1.py
