Metadata-Version: 1.1
Name: counterparty-lib
Version: 9.55.3
Summary: Counterparty Protocol Reference Implementation
Home-page: http://counterparty.io
Author: Counterparty Developers
Author-email: dev@counterparty.io
License: MIT
Download-URL: https://github.com/CounterpartyXCP/counterparty-lib/releases/tag/9.55.3
Keywords: counterparty,bitcoin
Platform: UNKNOWN
Classifier: Development Status :: 5 - Production/Stable
Classifier: Intended Audience :: Developers
Classifier: Intended Audience :: Financial and Insurance Industry
Classifier: License :: OSI Approved :: MIT License
Classifier: Natural Language :: English
Classifier: Operating System :: Microsoft :: Windows
Classifier: Operating System :: POSIX
Classifier: Programming Language :: Python :: 3 :: Only
Classifier: Topic :: Office/Business :: Financial
Classifier: Topic :: Software Development :: Libraries :: Python Modules
Classifier: Topic :: System :: Distributed Computing
Provides: counterpartylib
